comdexpy/__init__.py
comdexpy/client.py
comdexpy/constants.py
comdexpy/cosmos_app.py
comdexpy/exceptions.py
comdexpy/send_tx.py
comdexpy/transaction.py
comdexpy/utils.py
comdexpy/messages/__init__.py
comdexpy/messages/base.py
comdexpy/messages/comdex/__init__.py
comdexpy/messages/comdex/auction/__init__.py
comdexpy/messages/comdex/auction/msgs.py
comdexpy/messages/comdex/lend/__init__.py
comdexpy/messages/comdex/lend/msgs.py
comdexpy/messages/comdex/liquidation/__init__.py
comdexpy/messages/comdex/liquidation/msgs.py
comdexpy/messages/comdex/liquidity/__init__.py
comdexpy/messages/comdex/liquidity/msgs.py
comdexpy/messages/comdex/vault/__init__.py
comdexpy/messages/comdex/vault/msgs.py
comdexpy/messages/cosmos/__init__.py
comdexpy/messages/cosmos/bank/__init__.py
comdexpy/messages/cosmos/bank/msgs.py
comdexpy/proto/__init__.py
comdexpy/proto/amino/__init__.py
comdexpy/proto/comdex/__init__.py
comdexpy/proto/comdex/asset/__init__.py
comdexpy/proto/comdex/asset/v1beta1/__init__.py
comdexpy/proto/comdex/auction/__init__.py
comdexpy/proto/comdex/auction/v1beta1/__init__.py
comdexpy/proto/comdex/bandoracle/__init__.py
comdexpy/proto/comdex/bandoracle/v1beta1/__init__.py
comdexpy/proto/comdex/collector/__init__.py
comdexpy/proto/comdex/collector/v1beta1/__init__.py
comdexpy/proto/comdex/esm/__init__.py
comdexpy/proto/comdex/esm/v1beta1/__init__.py
comdexpy/proto/comdex/lend/__init__.py
comdexpy/proto/comdex/lend/v1beta1/__init__.py
comdexpy/proto/comdex/liquidation/__init__.py
comdexpy/proto/comdex/liquidation/v1beta1/__init__.py
comdexpy/proto/comdex/liquidity/__init__.py
comdexpy/proto/comdex/liquidity/v1beta1/__init__.py
comdexpy/proto/comdex/locker/__init__.py
comdexpy/proto/comdex/locker/v1beta1/__init__.py
comdexpy/proto/comdex/market/__init__.py
comdexpy/proto/comdex/market/v1beta1/__init__.py
comdexpy/proto/comdex/rewards/__init__.py
comdexpy/proto/comdex/rewards/v1beta1/__init__.py
comdexpy/proto/comdex/tokenmint/__init__.py
comdexpy-0.5.dist-info/LICENSE
comdexpy-0.5.dist-info/METADATA
comdexpy-0.5.dist-info/WHEEL
comdexpy-0.5.dist-info/top_level.txt
comdexpy-0.5.dist-info/RECORD
