Metadata-Version: 2.1
Name: comdexpy
Version: 0.5
Summary: Python SDK for interacting with comdex node
Author: Comdex
Author-email: <dheeraj@comdex.one>
Keywords: python,comdex,comdex sdk,comdexpy,pycomdex,comdex python sdk
Classifier: Development Status :: 4 - Beta
Classifier: Intended Audience :: Developers
Classifier: Programming Language :: Python :: 3
Classifier: Operating System :: Unix
Classifier: Operating System :: MacOS :: MacOS X
Classifier: Operating System :: Microsoft :: Windows
License-File: LICENSE
Requires-Dist: asn1crypto (==1.5.1)
Requires-Dist: base58 (==2.1.1)
Requires-Dist: bech32 (==1.2.0)
Requires-Dist: betterproto (==2.0.0b5)
Requires-Dist: bip32 (==3.4)
Requires-Dist: certifi (==2022.12.7)
Requires-Dist: cffi (==1.15.1)
Requires-Dist: charset-normalizer (==3.1.0)
Requires-Dist: coincurve (==18.0.0)
Requires-Dist: ecdsa (==0.18.0)
Requires-Dist: ECPy (==1.2.5)
Requires-Dist: future (==0.18.3)
Requires-Dist: grpcio (==1.53.0)
Requires-Dist: grpcio-tools (==1.53.0)
Requires-Dist: grpclib (==0.4.3)
Requires-Dist: h2 (==4.1.0)
Requires-Dist: hidapi (==0.13.1)
Requires-Dist: hpack (==4.0.0)
Requires-Dist: hyperframe (==6.0.1)
Requires-Dist: idna (==3.4)
Requires-Dist: ledgerblue (==0.1.46)
Requires-Dist: libusb1 (==3.0.0)
Requires-Dist: mnemonic (==0.20)
Requires-Dist: multidict (==6.0.4)
Requires-Dist: ndeflib (==0.3.3)
Requires-Dist: nfcpy (==1.0.4)
Requires-Dist: Pillow (==9.5.0)
Requires-Dist: protobuf (==4.22.3)
Requires-Dist: pycparser (==2.21)
Requires-Dist: pycryptodomex (==3.17)
Requires-Dist: pyDes (==2.0.1)
Requires-Dist: pyelftools (==0.29)
Requires-Dist: pyserial (==3.5)
Requires-Dist: python-dateutil (==2.8.2)
Requires-Dist: python-u2flib-host (==3.0.3)
Requires-Dist: requests (==2.28.2)
Requires-Dist: six (==1.16.0)
Requires-Dist: stringcase (==1.2.0)
Requires-Dist: urllib3 (==1.26.15)
Requires-Dist: websocket-client (==1.5.1)
